{
  "id": "1031610",
  "readings": [
    {
      "kanaExpression": "オーケストラ",
      "rank": 5938
    }
  ],
  "meanings": [
    {
      "lang": "en",
      "values": [
        "orchestra"
      ]
    },
    {
      "lang": "dut",
      "values": [
        "orkest"
      ]
    },
    {
      "lang": "fre",
      "values": [
        "orchestre"
      ]
    },
    {
      "lang": "ger",
      "values": [
        "Orchester"
      ]
    },
    {
      "lang": "hun",
      "values": [
        "zsöllye"
      ]
    },
    {
      "lang": "rus",
      "values": [
        "((англ.) orchestra)",
        "1) оркестр",
        "2) место для оркестра"
      ]
    },
    {
      "lang": "slv",
      "values": [
        "orkester"
      ]
    },
    {
      "lang": "spa",
      "values": [
        "orquesta (eng: orchestra)"
      ]
    },
    {
      "lang": "swe",
      "values": [
        "orkester"
      ]
    }
  ]
}