{
  "id": "1068830",
  "readings": [
    {
      "kanaExpression": "スケール",
      "rank": 6335
    }
  ],
  "meanings": [
    {
      "lang": "en",
      "values": [
        "scale",
        "vernier"
      ]
    },
    {
      "lang": "dut",
      "values": [
        "schaal",
        "omvang",
        "kaliber",
        "{wisk.} schaal",
        "weegschaal",
        "{muz.} toonschaal",
        "toonladder",
        "aanzetsel",
        "aanslag",
        "{ボイラーの} ketelsteen"
      ]
    },
    {
      "lang": "ger",
      "values": [
        "Skala",
        "Format",
        "Kaliber",
        "Maßstab",
        "Tonleiter",
        "Kesselstein",
        "Zunder"
      ]
    },
    {
      "lang": "hun",
      "values": [
        "acél vonalzó",
        "skill",
        "fémhab",
        "fokbeosztás",
        "halpénz",
        "hályog",
        "hangsor",
        "kazánkő",
        "lehámló réteg",
        "lépcső",
        "létra",
        "pernye",
        "skála",
        "számrendszer",
        "vízkő"
      ]
    },
    {
      "lang": "rus",
      "values": [
        "((англ.) scale)",
        "1) размер, масштаб",
        "2) (муз.) гамма"
      ]
    },
    {
      "lang": "swe",
      "values": [
        "nonieskala"
      ]
    }
  ]
}