{
  "id": "1081410",
  "readings": [
    {
      "kanaExpression": "データつうしん",
      "furiganaExpression": [],
      "ranking": 1317
    },
    {
      "kanjiExpression": "データ通信",
      "kanaExpression": "データつうしん",
      "furiganaExpression": [
        {
          "text": "データ"
        },
        {
          "text": "通",
          "annotation": "つう"
        },
        {
          "text": "信",
          "annotation": "しん"
        }
      ],
      "ranking": 1317
    }
  ],
  "meanings": [
    {
      "lang": "en",
      "values": [
        "data communication"
      ]
    },
    {
      "lang": "ger",
      "values": [
        "Datenübertragung",
        "Datenkommunikation"
      ]
    }
  ]
}