{
  "id": "1081470",
  "readings": [
    {
      "kanaExpression": "デーモン"
    }
  ],
  "meanings": [
    {
      "lang": "en",
      "values": [
        "demon",
        "daemon (in Unix, etc.)"
      ]
    },
    {
      "lang": "dut",
      "values": [
        "demon",
        "boze geest",
        "duivel",
        "{myth.} demon",
        "halfgod",
        "Damon"
      ]
    },
    {
      "lang": "ger",
      "values": [
        "Dämon"
      ]
    },
    {
      "lang": "hun",
      "values": [
        "gonosz szellem"
      ]
    },
    {
      "lang": "rus",
      "values": [
        "демон"
      ]
    }
  ]
}