{
  "id": "1098440",
  "readings": [
    {
      "kanaExpression": "バスケットボール",
      "furiganaExpression": [],
      "ranking": 8508
    }
  ],
  "meanings": [
    {
      "lang": "en",
      "values": [
        "basketball"
      ]
    },
    {
      "lang": "dut",
      "values": [
        "basketbal"
      ]
    },
    {
      "lang": "fre",
      "values": [
        "basketball"
      ]
    },
    {
      "lang": "ger",
      "values": [
        "Basketball"
      ]
    },
    {
      "lang": "hun",
      "values": [
        "kosárlabda"
      ]
    },
    {
      "lang": "rus",
      "values": [
        "((англ.) basket-ball)",
        "баскетбол"
      ]
    },
    {
      "lang": "slv",
      "values": [
        "košarka"
      ]
    },
    {
      "lang": "spa",
      "values": [
        "baloncesto (eng: basketball)"
      ]
    }
  ]
}