{
  "id": "1187420",
  "readings": [
    {
      "kanaExpression": "かぐう"
    },
    {
      "kanjiExpression": "仮寓",
      "furiganaExpression": [
        {
          "text": "仮",
          "annotation": "か"
        },
        {
          "text": "寓",
          "annotation": "ぐう"
        }
      ]
    }
  ],
  "meanings": [
    {
      "lang": "en",
      "values": [
        "temporary residence"
      ]
    },
    {
      "lang": "ger",
      "values": [
        "vorübergehender Wohnsitz",
        "zeitweilige Unterkunft",
        "provisorische Wohnung",
        "zeitweiliger Aufenthaltsort"
      ]
    },
    {
      "lang": "rus",
      "values": [
        "временное место жительства, временное жилище (пристанище)",
        "{～する} жить (остановиться) временно"
      ]
    }
  ]
}