{
  "id": "1203130",
  "readings": [
    {
      "kanaExpression": "かいがら",
      "furiganaExpression": [],
      "ranking": 2929
    },
    {
      "kanjiExpression": "貝殻",
      "kanaExpression": "かいがら",
      "furiganaExpression": [
        {
          "text": "貝",
          "annotation": "かい"
        },
        {
          "text": "殻",
          "annotation": "がら"
        }
      ],
      "ranking": 2929
    }
  ],
  "meanings": [
    {
      "lang": "en",
      "values": [
        "seashell",
        "shell"
      ]
    },
    {
      "lang": "dut",
      "values": [
        "{dierk.} schelp",
        "{海の} zeeschelp"
      ]
    },
    {
      "lang": "fre",
      "values": [
        "coquille"
      ]
    },
    {
      "lang": "ger",
      "values": [
        "Muschelschale"
      ]
    },
    {
      "lang": "hun",
      "values": [
        "csigaház",
        "héjszerkezet",
        "karosszérialemezek",
        "kéreg",
        "köpeny",
        "lövedék",
        "versenycsónak"
      ]
    },
    {
      "lang": "rus",
      "values": [
        "раковина (пустая)"
      ]
    },
    {
      "lang": "slv",
      "values": [
        "školjka"
      ]
    },
    {
      "lang": "spa",
      "values": [
        "concha",
        "caparazón",
        "coraza"
      ]
    },
    {
      "lang": "swe",
      "values": [
        "skal",
        "snäckskal"
      ]
    }
  ]
}