{
  "id": "1204540",
  "readings": [
    {
      "kanaExpression": "ふた"
    },
    {
      "kanaExpression": "フタ"
    },
    {
      "kanjiExpression": "蓋",
      "furiganaExpression": [
        {
          "text": "蓋",
          "annotation": "ふた"
        }
      ]
    }
  ],
  "meanings": [
    {
      "lang": "en",
      "values": [
        "cover",
        "lid",
        "cap"
      ]
    },
    {
      "lang": "dut",
      "values": [
        "deksel",
        "klep",
        "lid",
        "dop",
        "afsluiting",
        "{i.h.b.} stolp",
        "afsluitplaat",
        "afsluitdop",
        "afsluitklep",
        "{封筒の} sluitflap",
        "{dierk.} operculum",
        "sluitklep",
        "kieuwdeksel",
        "dekvlies"
      ]
    },
    {
      "lang": "fre",
      "values": [
        "couvercle",
        "capuchon",
        "opercule",
        "capsule"
      ]
    },
    {
      "lang": "hun",
      "values": [
        "fedél",
        "fedő",
        "rejtekhely",
        "ácsolat-ék",
        "ékfa",
        "tökfedő",
        "sapka",
        "tető"
      ]
    },
    {
      "lang": "rus",
      "values": [
        "крышка; покрышка, чехол; колпак; клапан (кармана)",
        "{～をする} накрывать; (перен.) держать в тайне"
      ]
    },
    {
      "lang": "slv",
      "values": [
        "pokrov"
      ]
    },
    {
      "lang": "spa",
      "values": [
        "tapa",
        "cubierta"
      ]
    }
  ]
}