{
  "id": "1219300",
  "readings": [
    {
      "kanaExpression": "きかい",
      "furiganaExpression": [],
      "ranking": 2929
    },
    {
      "kanjiExpression": "奇怪",
      "kanaExpression": "きかい",
      "furiganaExpression": [
        {
          "text": "奇",
          "annotation": "き"
        },
        {
          "text": "怪",
          "annotation": "かい"
        }
      ],
      "ranking": 2929
    }
  ],
  "meanings": [
    {
      "lang": "en",
      "values": [
        "strange",
        "wonderful",
        "weird",
        "outrageous",
        "mysterious"
      ]
    },
    {
      "lang": "dut",
      "values": [
        "vreemd",
        "raar",
        "merkwaardig",
        "wonderlijk",
        "zonderling",
        "eigenaardig",
        "wonderbaarlijk",
        "bizar",
        "gek",
        "bevreemdend",
        "laakbaar",
        "schandelijk",
        "schandalig",
        "ongehoord"
      ]
    },
    {
      "lang": "fre",
      "values": [
        "étrange",
        "bizarre",
        "extraordinaire",
        "mystérieux"
      ]
    },
    {
      "lang": "ger",
      "values": [
        "Mysteriösität",
        "Seltsamkeit",
        "Unheimlichkeit",
        "Befremdlichkeit",
        "mysteriös",
        "seltsam",
        "unheimlich",
        "befremdlich",
        "undurchsichtig",
        "geheimnisvoll",
        "rätselhaft",
        "verwunderlich",
        "unverzeihlich",
        "unverschämt",
        "Unerklärlichkeit",
        "Unerhörtheit",
        "Frechheit",
        "Unverschämtheit"
      ]
    },
    {
      "lang": "hun",
      "values": [
        "furcsa",
        "ismeretlen",
        "különös",
        "meglepő",
        "szokatlan",
        "bámulatos",
        "csodálatos",
        "csodás",
        "sors",
        "botrányos",
        "égbekiáltó",
        "felháborító",
        "gyötrő",
        "tikkasztó",
        "túlzott",
        "vérlázító",
        "misztikus",
        "erőszakos",
        "szörnyű"
      ]
    },
    {
      "lang": "rus",
      "values": [
        ": ～な",
        "1) странный, удивительный; невероятный",
        "2) достойный порицания, возмутительный; чудовищный; наглый"
      ]
    }
  ]
}