{
  "id": "1222690",
  "readings": [
    {
      "kanaExpression": "きりょく",
      "rank": 21500
    },
    {
      "kanjiExpression": "気力",
      "furiganaExpression": [
        {
          "text": "気",
          "annotation": "き"
        },
        {
          "text": "力",
          "annotation": "りょく"
        }
      ],
      "rank": 7187
    }
  ],
  "meanings": [
    {
      "lang": "en",
      "values": [
        "willpower",
        "energy",
        "vitality"
      ]
    },
    {
      "lang": "dut",
      "values": [
        "wilskracht",
        "karakter",
        "{sportt.} moraal",
        "energie",
        "vaart",
        "drive",
        "kracht",
        "vitaliteit",
        "gedrevenheid",
        "ruggengraat",
        "doorzettingsvermogen",
        "moed",
        "durf",
        "pit",
        "lef"
      ]
    },
    {
      "lang": "fre",
      "values": [
        "énergie",
        "vitalité",
        "volonté"
      ]
    },
    {
      "lang": "ger",
      "values": [
        "Geisteskraft",
        "Willenskraft",
        "Lebenskraft",
        "Tatkraft",
        "Energie",
        "Vitalität"
      ]
    },
    {
      "lang": "hun",
      "values": [
        "energia",
        "életerő"
      ]
    },
    {
      "lang": "rus",
      "values": [
        "1) энергия, жизнедеятельность, жизнеспособность; темперамент; пыл",
        "{～のある} энергичный; темпераментный",
        "2) действие (сила) сжатого воздуха"
      ]
    },
    {
      "lang": "spa",
      "values": [
        "fuerza",
        "energía",
        "vitalidad"
      ]
    }
  ]
}