{
  "id": "1291090",
  "readings": [
    {
      "kanaExpression": "さしひき",
      "rank": 23500
    },
    {
      "kanjiExpression": "差し引き",
      "furiganaExpression": [
        {
          "text": "差",
          "annotation": "さ"
        },
        {
          "text": "し"
        },
        {
          "text": "引",
          "annotation": "ひ"
        },
        {
          "text": "き"
        }
      ],
      "rank": 23500
    },
    {
      "kanjiExpression": "差引き",
      "furiganaExpression": [
        {
          "text": "差",
          "annotation": "さし"
        },
        {
          "text": "引",
          "annotation": "ひ"
        },
        {
          "text": "き"
        }
      ]
    },
    {
      "kanjiExpression": "差引",
      "furiganaExpression": [
        {
          "text": "差",
          "annotation": "さし"
        },
        {
          "text": "引",
          "annotation": "ひき"
        }
      ]
    }
  ],
  "meanings": [
    {
      "lang": "en",
      "values": [
        "deduction",
        "subtraction",
        "balance",
        "ebb and flow",
        "rise and fall"
      ]
    },
    {
      "lang": "dut",
      "values": [
        "aftrekking",
        "aftrek",
        "inhouding",
        "vermindering",
        "mindering",
        "korting",
        "saldo",
        "overschot",
        "tegoed",
        "afwisseling van eb en vloed",
        "getijwisseling"
      ]
    },
    {
      "lang": "fre",
      "values": [
        "déduction",
        "retenue",
        "soustraction",
        "solde",
        "balance (d\u0027un compte)",
        "flux et reflux",
        "ascension et chute"
      ]
    },
    {
      "lang": "ger",
      "values": [
        "Abzug",
        "Bilanz",
        "Saldo",
        "Überschuss",
        "Rest",
        "Ebbe und Flut",
        "Gezeiten"
      ]
    },
    {
      "lang": "hun",
      "values": [
        "következtetés",
        "levezetés",
        "levonás",
        "maradék",
        "megfontoltság",
        "szilárdság"
      ]
    },
    {
      "lang": "rus",
      "values": [
        "1) вычитание; вычет",
        "2) остаток; баланс",
        "{～する} подводить баланс",
        "3) прилив и отлив",
        "{～する} приливать и отливать",
        "4) повышение и понижение",
        "{～する} повышаться и понижаться; перемежаться"
      ]
    },
    {
      "lang": "slv",
      "values": [
        "odtegljaj",
        "odvzem",
        "odšteti",
        "odtegniti",
        "odštevanje"
      ]
    },
    {
      "lang": "spa",
      "values": [
        "reducción",
        "sustracción",
        "saldo",
        "balance"
      ]
    }
  ]
}