{
  "id": "1310060",
  "readings": [
    {
      "kanaExpression": "しれい",
      "furiganaExpression": [],
      "ranking": 5000
    },
    {
      "kanjiExpression": "指令",
      "kanaExpression": "しれい",
      "furiganaExpression": [
        {
          "text": "指",
          "annotation": "し"
        },
        {
          "text": "令",
          "annotation": "れい"
        }
      ],
      "ranking": 5000
    }
  ],
  "meanings": [
    {
      "lang": "en",
      "values": [
        "orders",
        "instructions",
        "directive",
        "command"
      ]
    },
    {
      "lang": "dut",
      "values": [
        "bevel",
        "order",
        "opdracht",
        "instructie",
        "gebod",
        "sommatie",
        "last",
        "richtlijn",
        "directief",
        "voorschrift",
        "verordening",
        "{jur.} injunctie",
        "{jur.} aanwijzing (voor advocaat)",
        "bevelen",
        "verordenen",
        "gelasten",
        "opdragen",
        "gebieden",
        "commanderen",
        "instrueren",
        "voorschrijven",
        "dicteren",
        "opleggen",
        "last geven"
      ]
    },
    {
      "lang": "fre",
      "values": [
        "directive",
        "instructions",
        "ordres"
      ]
    },
    {
      "lang": "ger",
      "values": [
        "Verordnung",
        "Anordnung",
        "Instruktion",
        "Richtlinie",
        "Direktive",
        "Befehl",
        "Anweisung geben",
        "anweisen"
      ]
    },
    {
      "lang": "hun",
      "values": [
        "csapatok",
        "parancsnokság",
        "rendelkezés vmivel",
        "uralkodás vmi felett",
        "vezénylés",
        "vezényszó"
      ]
    },
    {
      "lang": "rus",
      "values": [
        "приказ, приказание, предписание, указание, директива",
        "{～する} приказывать, предписывать; давать указания (директивы)"
      ]
    },
    {
      "lang": "slv",
      "values": [
        "navodilo",
        "ukaz"
      ]
    },
    {
      "lang": "spa",
      "values": [
        "ordenes",
        "instrucciones"
      ]
    }
  ]
}