{
  "id": "1387190",
  "readings": [
    {
      "kanaExpression": "せんたん",
      "rank": 32500
    },
    {
      "kanjiExpression": "仙丹",
      "furiganaExpression": [
        {
          "text": "仙",
          "annotation": "せん"
        },
        {
          "text": "丹",
          "annotation": "たん"
        }
      ]
    }
  ],
  "meanings": [
    {
      "lang": "en",
      "values": [
        "elixir (of life)"
      ]
    },
    {
      "lang": "ger",
      "values": [
        "Elixier der Unsterblichkeit"
      ]
    },
    {
      "lang": "rus",
      "values": [
        "чудодейственные пилюли, пилюли жизни"
      ]
    },
    {
      "lang": "swe",
      "values": [
        "livselixir"
      ]
    }
  ]
}