{
  "id": "1396890",
  "readings": [
    {
      "kanaExpression": "そしゃくち"
    },
    {
      "kanjiExpression": "租借地",
      "furiganaExpression": [
        {
          "text": "租",
          "annotation": "そ"
        },
        {
          "text": "借",
          "annotation": "しゃく"
        },
        {
          "text": "地",
          "annotation": "ち"
        }
      ]
    }
  ],
  "meanings": [
    {
      "lang": "en",
      "values": [
        "leasehold land"
      ]
    },
    {
      "lang": "fre",
      "values": [
        "ferme (fermage)",
        "terre sous bail"
      ]
    },
    {
      "lang": "ger",
      "values": [
        "Pachtland",
        "ausländische Konzession",
        "einer fremden Macht zur Pacht überlassener Grund und Boden"
      ]
    },
    {
      "lang": "rus",
      "values": [
        "1) арендованный участок",
        "2) иностранный сеттльмент"
      ]
    },
    {
      "lang": "swe",
      "values": [
        "arrendejord"
      ]
    }
  ]
}