{
  "id": "1412160",
  "readings": [
    {
      "kanaExpression": "だいひつ",
      "furiganaExpression": [],
      "ranking": 15000
    },
    {
      "kanjiExpression": "代筆",
      "kanaExpression": "だいひつ",
      "furiganaExpression": [
        {
          "text": "代",
          "annotation": "だい"
        },
        {
          "text": "筆",
          "annotation": "ひつ"
        }
      ],
      "ranking": 15000
    }
  ],
  "meanings": [
    {
      "lang": "en",
      "values": [
        "writing on someone\u0027s behalf"
      ]
    },
    {
      "lang": "ger",
      "values": [
        "anstelle jmds. anderen schreiben",
        "stellvertretendes Schreiben (eines Briefes oder sonstigen Textes)",
        "anstelle jmds. anderen verfasstes Schreiben"
      ]
    },
    {
      "lang": "rus",
      "values": [
        "1): {～する} писать вместо другого",
        "2) (см.) だいひつにん"
      ]
    }
  ]
}