{
  "id": "1462540",
  "readings": [
    {
      "kanaExpression": "ふたりづれ"
    },
    {
      "kanjiExpression": "二人連れ",
      "furiganaExpression": [
        {
          "text": "二人",
          "annotation": "ふたり"
        },
        {
          "text": "連",
          "annotation": "づ"
        },
        {
          "text": "れ"
        }
      ]
    }
  ],
  "meanings": [
    {
      "lang": "en",
      "values": [
        "party of two"
      ]
    },
    {
      "lang": "ger",
      "values": [
        "Paar",
        "Pärchen"
      ]
    },
    {
      "lang": "rus",
      "values": [
        "пара (о людях)",
        "{～で} вдвоём"
      ]
    }
  ]
}