{
  "id": "1467320",
  "readings": [
    {
      "kanaExpression": "にんよう"
    },
    {
      "kanjiExpression": "任用",
      "furiganaExpression": [
        {
          "text": "任",
          "annotation": "にん"
        },
        {
          "text": "用",
          "annotation": "よう"
        }
      ]
    }
  ],
  "meanings": [
    {
      "lang": "en",
      "values": [
        "appointment",
        "employment"
      ]
    },
    {
      "lang": "dut",
      "values": [
        "aanstellen",
        "benoemen",
        "aanstelling",
        "benoeming"
      ]
    },
    {
      "lang": "ger",
      "values": [
        "anstellen als …",
        "einsetzen als …",
        "ernennen als …",
        "Anstellung",
        "Einsetzung",
        "Ernennung"
      ]
    },
    {
      "lang": "hun",
      "values": [
        "megbeszélt találkozó",
        "randevú",
        "találkozó"
      ]
    },
    {
      "lang": "rus",
      "values": [
        "назначение, принятие [на должность]",
        "{～する} назначать [на должность], принимать [на службу]"
      ]
    }
  ]
}