{
  "id": "1502840",
  "readings": [
    {
      "kanaExpression": "ふん",
      "rank": 10447
    },
    {
      "kanjiExpression": "分",
      "furiganaExpression": [
        {
          "text": "分",
          "annotation": "ふん"
        }
      ],
      "rank": 182
    }
  ],
  "meanings": [
    {
      "lang": "en",
      "values": [
        "minute (unit of time)",
        "fun (one tenth of a monme, 5.787 grains)"
      ]
    },
    {
      "lang": "dut",
      "values": [
        "{eenheid van massa} fun {ca. 0,375 gram; het tiende deel van een monme 匁; het tienvoud van een rin 厘}",
        "{tijdseenheid} minuut {het zestigste deel van een uur; het zestigvoud van een seconde}",
        "{schaaleenheid} minuut {het zestigste deel van een graad; het zestigvoud van een seconde}"
      ]
    },
    {
      "lang": "fre",
      "values": [
        "minute",
        "fun (un dixième de monme, 5.787 grains)"
      ]
    },
    {
      "lang": "ger",
      "values": [
        "Minute (Zeiteinheit)",
        "Minute (Winkeleinheit)",
        "Fun (ein Zehntel Monme)"
      ]
    },
    {
      "lang": "hun",
      "values": [
        "aprólékos",
        "ívperc",
        "memorandum",
        "perc"
      ]
    },
    {
      "lang": "rus",
      "values": [
        "1) минута",
        "2) фун (мера веса \u003d 0,375 грамма)",
        "\u003d 10 рин \u003d 0,375 г"
      ]
    },
    {
      "lang": "slv",
      "values": [
        "minut"
      ]
    },
    {
      "lang": "spa",
      "values": [
        "minuto"
      ]
    },
    {
      "lang": "swe",
      "values": [
        "minut"
      ]
    }
  ]
}