{
  "id": "1515890",
  "readings": [
    {
      "kanaExpression": "ほうけんしょう"
    },
    {
      "kanjiExpression": "奉献頌",
      "furiganaExpression": [
        {
          "text": "奉",
          "annotation": "ほう"
        },
        {
          "text": "献",
          "annotation": "けん"
        },
        {
          "text": "頌",
          "annotation": "しょう"
        }
      ]
    }
  ],
  "meanings": [
    {
      "lang": "en",
      "values": [
        "offertory",
        "offertory music"
      ]
    },
    {
      "lang": "ger",
      "values": [
        "Offertorium",
        "Gesang zum Offertorium"
      ]
    },
    {
      "lang": "hun",
      "values": [
        "offertórium",
        "összegyűjtött adomány",
        "perselyezés"
      ]
    }
  ]
}