{
  "id": "1515580",
  "readings": [
    {
      "kanaExpression": "あきれる"
    },
    {
      "kanjiExpression": "呆れる",
      "furiganaExpression": [
        {
          "text": "呆",
          "annotation": "あき"
        },
        {
          "text": "れる"
        }
      ]
    },
    {
      "kanjiExpression": "惘れる",
      "furiganaExpression": [
        {
          "text": "惘",
          "annotation": "あき"
        },
        {
          "text": "れる"
        }
      ]
    }
  ],
  "meanings": [
    {
      "lang": "en",
      "values": [
        "to be amazed",
        "to be shocked",
        "to be astonished",
        "to be astounded",
        "to be disgusted",
        "to be exasperated",
        "to be fed up"
      ]
    },
    {
      "lang": "dut",
      "values": [
        "verbaasd zijn",
        "verwonderd zijn",
        "versteld staan",
        "verstomd staan",
        "stomverbaasd zijn",
        "verbouwereerd zijn",
        "ontsteld zijn",
        "ontzet zijn",
        "geschokt zijn",
        "gechoqueerd zijn",
        "verontwaardigd zijn",
        "zich ergeren aan",
        "walgen van"
      ]
    },
    {
      "lang": "fre",
      "values": [
        "être ébahi",
        "être abasourdi",
        "être choqué",
        "être stupéfait",
        "être dégoûté",
        "être exaspéré"
      ]
    },
    {
      "lang": "ger",
      "values": [
        "verblüfft sein",
        "sprachlos sein",
        "eines Dinges überdrüssig werden",
        "jmdm. verleidet werden"
      ]
    },
    {
      "lang": "rus",
      "values": [
        "быть изумлённым, быть озадаченным; негодовать, возмущаться",
        "(ср.) あきれた"
      ]
    },
    {
      "lang": "spa",
      "values": [
        "asombrarse",
        "pasmarse"
      ]
    }
  ]
}