{
  "id": "1520630",
  "readings": [
    {
      "kanaExpression": "ほっぺた",
      "rank": 23508
    },
    {
      "kanjiExpression": "頬っぺた",
      "furiganaExpression": [
        {
          "text": "頬",
          "annotation": "ほ"
        },
        {
          "text": "っぺた"
        }
      ],
      "rank": 23508
    },
    {
      "kanjiExpression": "頰っぺた",
      "furiganaExpression": [
        {
          "text": "頰",
          "annotation": "ほ"
        },
        {
          "text": "っぺた"
        }
      ]
    },
    {
      "kanjiExpression": "頬っ辺",
      "furiganaExpression": [
        {
          "text": "頬",
          "annotation": "ほ"
        },
        {
          "text": "っ"
        },
        {
          "text": "辺",
          "annotation": "ぺた"
        }
      ]
    },
    {
      "kanjiExpression": "頰っ辺",
      "furiganaExpression": [
        {
          "text": "頰",
          "annotation": "ほ"
        },
        {
          "text": "っ"
        },
        {
          "text": "辺",
          "annotation": "ぺた"
        }
      ]
    }
  ],
  "meanings": [
    {
      "lang": "en",
      "values": [
        "cheek"
      ]
    },
    {
      "lang": "dut",
      "values": [
        "wang",
        "kaak",
        "koon"
      ]
    },
    {
      "lang": "fre",
      "values": [
        "joue"
      ]
    },
    {
      "lang": "ger",
      "values": [
        "Backe",
        "Wange"
      ]
    },
    {
      "lang": "hun",
      "values": [
        "orca",
        "pofátlanság"
      ]
    },
    {
      "lang": "rus",
      "values": [
        "(прост.) щёки; щёчки"
      ]
    },
    {
      "lang": "slv",
      "values": [
        "lice"
      ]
    },
    {
      "lang": "spa",
      "values": [
        "mejilla",
        "cachete"
      ]
    }
  ]
}