{
  "id": "1599670",
  "readings": [
    {
      "kanaExpression": "なみはずれる",
      "furiganaExpression": [],
      "ranking": 19500
    },
    {
      "kanjiExpression": "並外れる",
      "kanaExpression": "なみはずれる",
      "furiganaExpression": [
        {
          "text": "並",
          "annotation": "なみ"
        },
        {
          "text": "外",
          "annotation": "はず"
        },
        {
          "text": "れる"
        }
      ],
      "ranking": 19500
    }
  ],
  "meanings": [
    {
      "lang": "en",
      "values": [
        "to be uncommon"
      ]
    },
    {
      "lang": "ger",
      "values": [
        "außergewöhnlich sein",
        "ungewöhnlich sein"
      ]
    },
    {
      "lang": "rus",
      "values": [
        "выдаваться, выделяться"
      ]
    }
  ]
}