{
  "id": "1601750",
  "readings": [
    {
      "kanaExpression": "ひきとめる",
      "rank": 23508
    },
    {
      "kanjiExpression": "引き止める",
      "furiganaExpression": [
        {
          "text": "引",
          "annotation": "ひ"
        },
        {
          "text": "き"
        },
        {
          "text": "止",
          "annotation": "と"
        },
        {
          "text": "める"
        }
      ],
      "rank": 23508
    },
    {
      "kanjiExpression": "引き留める",
      "furiganaExpression": [
        {
          "text": "引",
          "annotation": "ひ"
        },
        {
          "text": "き"
        },
        {
          "text": "留",
          "annotation": "と"
        },
        {
          "text": "める"
        }
      ]
    },
    {
      "kanjiExpression": "引きとめる",
      "furiganaExpression": [
        {
          "text": "引",
          "annotation": "ひ"
        },
        {
          "text": "きとめる"
        }
      ]
    },
    {
      "kanjiExpression": "引止める",
      "furiganaExpression": [
        {
          "text": "引",
          "annotation": "ひき"
        },
        {
          "text": "止",
          "annotation": "と"
        },
        {
          "text": "める"
        }
      ],
      "rank": 23508
    },
    {
      "kanjiExpression": "引留める",
      "furiganaExpression": [
        {
          "text": "引",
          "annotation": "ひき"
        },
        {
          "text": "留",
          "annotation": "と"
        },
        {
          "text": "める"
        }
      ]
    },
    {
      "kanjiExpression": "ひき止める",
      "furiganaExpression": [
        {
          "text": "ひき"
        },
        {
          "text": "止",
          "annotation": "と"
        },
        {
          "text": "める"
        }
      ]
    },
    {
      "kanjiExpression": "ひき留める",
      "furiganaExpression": [
        {
          "text": "ひき"
        },
        {
          "text": "留",
          "annotation": "と"
        },
        {
          "text": "める"
        }
      ]
    }
  ],
  "meanings": [
    {
      "lang": "en",
      "values": [
        "to detain",
        "to check",
        "to restrain",
        "to stop"
      ]
    },
    {
      "lang": "dut",
      "values": [
        "ophouden",
        "beletten (voort) te gaan",
        "tegenhouden",
        "staande houden",
        "{話をしかけて} aanspreken",
        "aanklampen",
        "accosteren",
        "aborderen",
        "{fig.} enteren",
        "{fig.} praaien",
        "{w.g.",
        "inform.} attaqueren",
        "{veroud.",
        "gew.} aanranden"
      ]
    },
    {
      "lang": "fre",
      "values": [
        "arrêter (quelqu\u0027un)",
        "retenir",
        "détenir",
        "contrôler",
        "limiter",
        "restreindre"
      ]
    },
    {
      "lang": "ger",
      "values": [
        "aufhalten",
        "zurückhalten",
        "vom Gehen abhalten",
        "am Gehen hindern",
        "hindern",
        "hinderlich sein",
        "im Weg stehen"
      ]
    },
    {
      "lang": "hun",
      "values": [
        "akadályoz",
        "feltart",
        "gátol",
        "visszatart",
        "átolvas",
        "ellenőriz",
        "féken tart",
        "megáll",
        "megdorgál",
        "megjelöl",
        "megtorpan",
        "mérsékel",
        "visszafojt",
        "korlátoz",
        "megfékez"
      ]
    },
    {
      "lang": "rus",
      "values": [
        "удерживать, задерживать ((напр.) гостя)"
      ]
    },
    {
      "lang": "slv",
      "values": [
        "preprečiti, zadržati (ne pustiti oditi)"
      ]
    },
    {
      "lang": "spa",
      "values": [
        "detener",
        "comprobar",
        "contener",
        "contenerse",
        "reprimir"
      ]
    }
  ]
}