{
  "id": "1616650",
  "readings": [
    {
      "kanaExpression": "だでん"
    },
    {
      "kanjiExpression": "打電",
      "furiganaExpression": [
        {
          "text": "打",
          "annotation": "だ"
        },
        {
          "text": "電",
          "annotation": "でん"
        }
      ]
    }
  ],
  "meanings": [
    {
      "lang": "en",
      "values": [
        "sending a telegram",
        "telegraphing",
        "wiring"
      ]
    },
    {
      "lang": "ger",
      "values": [
        "Telegrafieren",
        "Drahten",
        "Funken",
        "Telegramm absenden",
        "telegrafieren",
        "funken",
        "drahten"
      ]
    },
    {
      "lang": "hun",
      "values": [
        "távíró"
      ]
    },
    {
      "lang": "rus",
      "values": [
        "телеграфирование",
        "{～する} телеграфировать, посылать телеграмму"
      ]
    }
  ]
}