{
  "id": "1649490",
  "readings": [
    {
      "kanaExpression": "はちじゅう"
    },
    {
      "kanaExpression": "やそ"
    },
    {
      "kanjiExpression": "八十",
      "furiganaExpression": [
        {
          "text": "八",
          "annotation": "はち"
        },
        {
          "text": "十",
          "annotation": "じゅう"
        }
      ]
    }
  ],
  "meanings": [
    {
      "lang": "en",
      "values": [
        "eighty",
        "80"
      ]
    },
    {
      "lang": "ger",
      "values": [
        "achtzig",
        "80"
      ]
    },
    {
      "lang": "hun",
      "values": [
        "nyolcvan"
      ]
    },
    {
      "lang": "rus",
      "values": [
        "восемьдесят"
      ]
    },
    {
      "lang": "spa",
      "values": [
        "ochenta"
      ]
    },
    {
      "lang": "swe",
      "values": [
        "åttio"
      ]
    }
  ]
}