{
  "id": "1809690",
  "readings": [
    {
      "kanaExpression": "たかせ",
      "rank": 26000
    },
    {
      "kanjiExpression": "高瀬",
      "furiganaExpression": [
        {
          "text": "高",
          "annotation": "たか"
        },
        {
          "text": "瀬",
          "annotation": "せ"
        }
      ],
      "rank": 26000
    }
  ],
  "meanings": [
    {
      "lang": "en",
      "values": [
        "shallow river",
        "shallows",
        "flatboat",
        "river boat"
      ]
    },
    {
      "lang": "ger",
      "values": [
        "Furt",
        "Boot mit flachem Boden (Abk.)",
        "Takase (Ortschaft im Westen der Präf. Kagawa)",
        "Takase"
      ]
    }
  ]
}