{
  "id": "1821870",
  "readings": [
    {
      "kanaExpression": "らんばい",
      "furiganaExpression": [],
      "ranking": 7500
    },
    {
      "kanjiExpression": "乱売",
      "kanaExpression": "らんばい",
      "furiganaExpression": [
        {
          "text": "乱",
          "annotation": "らん"
        },
        {
          "text": "売",
          "annotation": "ばい"
        }
      ],
      "ranking": 7500
    }
  ],
  "meanings": [
    {
      "lang": "en",
      "values": [
        "underselling",
        "panic selling"
      ]
    },
    {
      "lang": "ger",
      "values": [
        "mit Verlust verkaufen",
        "zu Schleuderpreisen verkaufen",
        "Dumping",
        "Verkauf zum Schleuderpreis"
      ]
    },
    {
      "lang": "rus",
      "values": [
        ": {～する} распродавать, продавать за бесценок"
      ]
    }
  ]
}