{
  "id": "1832860",
  "readings": [
    {
      "kanaExpression": "しょくぎょうびょう"
    },
    {
      "kanjiExpression": "職業病",
      "furiganaExpression": [
        {
          "text": "職",
          "annotation": "しょく"
        },
        {
          "text": "業",
          "annotation": "ぎょう"
        },
        {
          "text": "病",
          "annotation": "びょう"
        }
      ]
    }
  ],
  "meanings": [
    {
      "lang": "en",
      "values": [
        "occupational disease"
      ]
    },
    {
      "lang": "dut",
      "values": [
        "beroepsziekte"
      ]
    },
    {
      "lang": "ger",
      "values": [
        "Berufskrankheit",
        "Berufserkrankung"
      ]
    },
    {
      "lang": "hun",
      "values": [
        "foglalkozási betegségek"
      ]
    },
    {
      "lang": "rus",
      "values": [
        "профессиональная болезнь"
      ]
    },
    {
      "lang": "swe",
      "values": [
        "yrkessjukdom"
      ]
    }
  ]
}