{
  "id": "1887570",
  "readings": [
    {
      "kanaExpression": "せいこく"
    },
    {
      "kanjiExpression": "靖国",
      "furiganaExpression": [
        {
          "text": "靖",
          "annotation": "せい"
        },
        {
          "text": "国",
          "annotation": "こく"
        }
      ],
      "rank": 5405
    }
  ],
  "meanings": [
    {
      "lang": "en",
      "values": [
        "pacifying the nation"
      ]
    },
    {
      "lang": "dut",
      "values": [
        "pacificatie van het land",
        "het tot rust brengen van de natie"
      ]
    },
    {
      "lang": "ger",
      "values": [
        "friedliche Regierung des Landes",
        "Befriedung des Landes"
      ]
    }
  ]
}