{
  "id": "1955650",
  "readings": [
    {
      "kanaExpression": "ほうしゃ"
    },
    {
      "kanaExpression": "ホウしゃ"
    },
    {
      "kanjiExpression": "硼砂",
      "furiganaExpression": [
        {
          "text": "硼",
          "annotation": "ほう"
        },
        {
          "text": "砂",
          "annotation": "しゃ"
        }
      ]
    },
    {
      "kanjiExpression": "ホウ砂",
      "furiganaExpression": [
        {
          "text": "ホウ"
        },
        {
          "text": "砂",
          "annotation": "しゃ"
        }
      ]
    }
  ],
  "meanings": [
    {
      "lang": "en",
      "values": [
        "borax"
      ]
    },
    {
      "lang": "ger",
      "values": [
        "Borax (Natriumsalz der Borsäure)"
      ]
    },
    {
      "lang": "rus",
      "values": [
        "бура"
      ]
    },
    {
      "lang": "swe",
      "values": [
        "borax"
      ]
    }
  ]
}