{
  "id": "2055740",
  "readings": [
    {
      "kanaExpression": "しのぎをけずる"
    },
    {
      "kanjiExpression": "しのぎを削る",
      "furiganaExpression": [
        {
          "text": "しのぎを"
        },
        {
          "text": "削",
          "annotation": "けず"
        },
        {
          "text": "る"
        }
      ]
    },
    {
      "kanjiExpression": "鎬を削る",
      "furiganaExpression": [
        {
          "text": "鎬",
          "annotation": "しのぎ"
        },
        {
          "text": "を"
        },
        {
          "text": "削",
          "annotation": "けず"
        },
        {
          "text": "る"
        }
      ]
    }
  ],
  "meanings": [
    {
      "lang": "en",
      "values": [
        "to compete ruthlessly",
        "to sharpen swords"
      ]
    },
    {
      "lang": "dut",
      "values": [
        "een verwoed gevecht leveren",
        "vinnig strijden"
      ]
    },
    {
      "lang": "ger",
      "values": [
        "aufs Heftigste kämpfen",
        "scharf konkurrieren"
      ]
    }
  ]
}