{
  "id": "2104790",
  "readings": [
    {
      "kanaExpression": "せいかんたい",
      "furiganaExpression": [],
      "ranking": 1317
    },
    {
      "kanjiExpression": "性感帯",
      "kanaExpression": "せいかんたい",
      "furiganaExpression": [
        {
          "text": "性",
          "annotation": "せい"
        },
        {
          "text": "感",
          "annotation": "かん"
        },
        {
          "text": "帯",
          "annotation": "たい"
        }
      ],
      "ranking": 1317
    }
  ],
  "meanings": [
    {
      "lang": "en",
      "values": [
        "erogenous zone"
      ]
    },
    {
      "lang": "ger",
      "values": [
        "erogene Zone"
      ]
    },
    {
      "lang": "spa",
      "values": [
        "zona erógena"
      ]
    }
  ]
}