{
  "id": "2454910",
  "readings": [
    {
      "kanaExpression": "ろくする"
    },
    {
      "kanjiExpression": "勒する",
      "furiganaExpression": [
        {
          "text": "勒",
          "annotation": "ろく"
        },
        {
          "text": "する"
        }
      ]
    }
  ],
  "meanings": [
    {
      "lang": "en",
      "values": [
        "to manage",
        "to carve",
        "to write (for posterity)"
      ]
    },
    {
      "lang": "ger",
      "values": [
        "kontrollieren",
        "anführen",
        "Zeichen eingravieren"
      ]
    }
  ]
}