{
  "id": "2527180",
  "readings": [
    {
      "kanaExpression": "かはく"
    },
    {
      "kanjiExpression": "下膊",
      "furiganaExpression": [
        {
          "text": "下",
          "annotation": "か"
        },
        {
          "text": "膊",
          "annotation": "はく"
        }
      ]
    }
  ],
  "meanings": [
    {
      "lang": "en",
      "values": [
        "forearm"
      ]
    },
    {
      "lang": "ger",
      "values": [
        "Unterarm",
        "Vorderarm",
        "Vorarm",
        "Antebrachium"
      ]
    }
  ]
}